mp_reader/__init__.py
mp_reader/__main__.py
mp_reader/analyzer.py
mp_reader/cli_tools.py
mp_reader/color.py
mp_reader/loader.py
mp_reader/malloc_stats.py
mp_reader/tree.py
mp_reader-0.1.2.dist-info/METADATA
mp_reader-0.1.2.dist-info/WHEEL
mp_reader-0.1.2.dist-info/entry_points.txt
mp_reader-0.1.2.dist-info/top_level.txt
mp_reader-0.1.2.dist-info/RECORD
