Metadata-Version: 2.4
Name: mp_reader
Version: 0.1.2
Summary: Add your description here
Requires-Python: >=3.13
Requires-Dist: cattrs>=25.1.1
Requires-Dist: numpy>=2.3.3
Requires-Dist: typer>=0.16.1
